{
	"name": "Source_vnxt_Reporting_copy1",
	"properties": {
		"linkedServiceName": {
			"referenceName": "vnxt_reporting",
			"type": "LinkedServiceReference"
		},
		"folder": {
			"name": "Reporting Dataset/Source report"
		},
		"annotations": [],
		"type": "AzureSqlMITable",
		"schema": [
			{
				"name": "ID",
				"type": "int",
				"precision": 10
			},
			{
				"name": "GRSListId",
				"type": "smallint",
				"precision": 5
			},
			{
				"name": "GRSDataSourceID",
				"type": "smallint",
				"precision": 5
			},
			{
				"name": "ParentAccountID",
				"type": "uniqueidentifier"
			},
			{
				"name": "ParentAccountNumber",
				"type": "varchar"
			},
			{
				"name": "AccountID",
				"type": "uniqueidentifier"
			},
			{
				"name": "AccountNumber",
				"type": "varchar"
			},
			{
				"name": "ContactID",
				"type": "uniqueidentifier"
			},
			{
				"name": "ContactNumber",
				"type": "varchar"
			},
			{
				"name": "PartnerID",
				"type": "uniqueidentifier"
			},
			{
				"name": "PartnerNumber",
				"type": "varchar"
			},
			{
				"name": "ParentPartnerID",
				"type": "uniqueidentifier"
			},
			{
				"name": "ParentPartnerNumber",
				"type": "varchar"
			},
			{
				"name": "PartnerAccountID",
				"type": "uniqueidentifier"
			},
			{
				"name": "PartnerAccountNumber",
				"type": "varchar"
			},
			{
				"name": "MPLID",
				"type": "varchar"
			},
			{
				"name": "MPNID",
				"type": "varchar"
			},
			{
				"name": "MSSalesTopParentID",
				"type": "varchar"
			},
			{
				"name": "MSSalesID",
				"type": "varchar"
			},
			{
				"name": "Prefix",
				"type": "nvarchar"
			},
			{
				"name": "FirstName",
				"type": "nvarchar"
			},
			{
				"name": "MiddleName",
				"type": "nvarchar"
			},
			{
				"name": "LastName",
				"type": "nvarchar"
			},
			{
				"name": "EmailAddress",
				"type": "nvarchar"
			},
			{
				"name": "MainPhoneNumber",
				"type": "nvarchar"
			},
			{
				"name": "MobilePhone",
				"type": "nvarchar"
			},
			{
				"name": "Fax",
				"type": "nvarchar"
			},
			{
				"name": "StreetAddress",
				"type": "nvarchar"
			},
			{
				"name": "City",
				"type": "nvarchar"
			},
			{
				"name": "State",
				"type": "nvarchar"
			},
			{
				"name": "PostalCode",
				"type": "nvarchar"
			},
			{
				"name": "Sector",
				"type": "nvarchar"
			},
			{
				"name": "JobTitle",
				"type": "nvarchar"
			},
			{
				"name": "JobRole",
				"type": "nvarchar"
			},
			{
				"name": "AccountManager",
				"type": "nvarchar"
			},
			{
				"name": "OrganizationTypeID",
				"type": "smallint",
				"precision": 5
			},
			{
				"name": "ContactTypeID",
				"type": "smallint",
				"precision": 5
			},
			{
				"name": "Vertical",
				"type": "varchar"
			},
			{
				"name": "VerticalIndustry",
				"type": "varchar"
			},
			{
				"name": "Industry",
				"type": "varchar"
			},
			{
				"name": "Tier",
				"type": "varchar"
			},
			{
				"name": "TierLevelID",
				"type": "smallint",
				"precision": 5
			},
			{
				"name": "CompanyName",
				"type": "nvarchar"
			},
			{
				"name": "SalesDistrict",
				"type": "nvarchar"
			},
			{
				"name": "SalesSubDistrict",
				"type": "nvarchar"
			},
			{
				"name": "SalesRegion",
				"type": "nvarchar"
			},
			{
				"name": "AreaID",
				"type": "smallint",
				"precision": 5
			},
			{
				"name": "RegionID",
				"type": "smallint",
				"precision": 5
			},
			{
				"name": "SubRegionID",
				"type": "smallint",
				"precision": 5
			},
			{
				"name": "SubsidiaryID",
				"type": "smallint",
				"precision": 5
			},
			{
				"name": "CountryId",
				"type": "smallint",
				"precision": 5
			},
			{
				"name": "SegmentId",
				"type": "smallint",
				"precision": 5
			},
			{
				"name": "SubSegmentId",
				"type": "smallint",
				"precision": 5
			},
			{
				"name": "EngagementTypeID",
				"type": "smallint",
				"precision": 5
			},
			{
				"name": "DetailedEngagementTypeID",
				"type": "smallint",
				"precision": 5
			},
			{
				"name": "MarketAudienceID",
				"type": "smallint",
				"precision": 5
			},
			{
				"name": "PrimaryMarketAudienceID",
				"type": "smallint",
				"precision": 5
			},
			{
				"name": "AllowCalls",
				"type": "bit"
			},
			{
				"name": "AllowDMail",
				"type": "bit"
			},
			{
				"name": "AllowEMail",
				"type": "bit"
			},
			{
				"name": "KeyContact",
				"type": "bit"
			},
			{
				"name": "ManagedAccount",
				"type": "bit"
			},
			{
				"name": "ManagedContact",
				"type": "bit"
			},
			{
				"name": "DecisionMakerFlag",
				"type": "smallint",
				"precision": 5
			},
			{
				"name": "PreferredLanguageId",
				"type": "smallint",
				"precision": 5
			},
			{
				"name": "MPNHeadQuartersId",
				"type": "varchar"
			},
			{
				"name": "MPNLocationId",
				"type": "varchar"
			},
			{
				"name": "VOrganizationID",
				"type": "uniqueidentifier"
			},
			{
				"name": "VOrganizationNumber",
				"type": "varchar"
			},
			{
				"name": "VOrganization_PartnerID",
				"type": "uniqueidentifier"
			},
			{
				"name": "VOrganization_PartnerNumber",
				"type": "varchar"
			},
			{
				"name": "PCCount",
				"type": "varchar"
			},
			{
				"name": "NumberOfEmployees",
				"type": "varchar"
			},
			{
				"name": "OrganizationID",
				"type": "uniqueidentifier"
			},
			{
				"name": "OrganizationNumber",
				"type": "varchar"
			},
			{
				"name": "ParentOrganizationID",
				"type": "uniqueidentifier"
			},
			{
				"name": "ParentOrganizationNumber",
				"type": "varchar"
			},
			{
				"name": "PartnerOrganizationID",
				"type": "uniqueidentifier"
			},
			{
				"name": "PartnerOrganizationNumber",
				"type": "varchar"
			},
			{
				"name": "SourceLanguage",
				"type": "nvarchar"
			},
			{
				"name": "PartnerTypeID",
				"type": "smallint",
				"precision": 5
			},
			{
				"name": "PartnerSubTypeID",
				"type": "smallint",
				"precision": 5
			},
			{
				"name": "OrganizationPartnerTypeID",
				"type": "smallint",
				"precision": 5
			},
			{
				"name": "EnrollmentStatusID",
				"type": "smallint",
				"precision": 5
			},
			{
				"name": "ParentingLevelID",
				"type": "smallint",
				"precision": 5
			},
			{
				"name": "CompetencyID",
				"type": "smallint",
				"precision": 5
			},
			{
				"name": "ActiveCompetencies",
				"type": "varchar"
			},
			{
				"name": "ContactTypePriority",
				"type": "smallint",
				"precision": 5
			},
			{
				"name": "EnrollmentPriority",
				"type": "smallint",
				"precision": 5
			},
			{
				"name": "TierLevelPriority",
				"type": "smallint",
				"precision": 5
			},
			{
				"name": "Priority",
				"type": "smallint",
				"precision": 5
			},
			{
				"name": "PartnerName",
				"type": "nvarchar"
			},
			{
				"name": "IsMaps",
				"type": "bit"
			},
			{
				"name": "IsMapsSP",
				"type": "bit"
			},
			{
				"name": "IsMapsDD",
				"type": "bit"
			},
			{
				"name": "RejectionCount",
				"type": "smallint",
				"precision": 5
			},
			{
				"name": "RejectionSubTypes",
				"type": "nvarchar"
			},
			{
				"name": "IsFixable",
				"type": "varchar"
			},
			{
				"name": "DeDupeContactTypeID",
				"type": "smallint",
				"precision": 5
			},
			{
				"name": "InsertedOn",
				"type": "datetime",
				"precision": 23,
				"scale": 3
			},
			{
				"name": "InsertedBy",
				"type": "varchar"
			},
			{
				"name": "OCPCRMID",
				"type": "nvarchar"
			},
			{
				"name": "PartnerOneSubID",
				"type": "nvarchar"
			},
			{
				"name": "PartnerOneID",
				"type": "nvarchar"
			},
			{
				"name": "PartnerOneName",
				"type": "nvarchar"
			},
			{
				"name": "PartnerSpecialization",
				"type": "varchar"
			},
			{
				"name": "PartnerSubSpecialization",
				"type": "varchar"
			},
			{
				"name": "Engagement",
				"type": "nvarchar"
			},
			{
				"name": "GlobalCoverage",
				"type": "nvarchar"
			},
			{
				"name": "PrimaryPDM",
				"type": "nvarchar"
			},
			{
				"name": "CSA",
				"type": "nvarchar"
			},
			{
				"name": "PMA",
				"type": "nvarchar"
			},
			{
				"name": "PDMR",
				"type": "nvarchar"
			},
			{
				"name": "IsEngaged",
				"type": "bit"
			},
			{
				"name": "HasValidPDM",
				"type": "bit"
			},
			{
				"name": "IsManaged",
				"type": "bit"
			},
			{
				"name": "IsDelete",
				"type": "bit"
			},
			{
				"name": "oemsegmenttype",
				"type": "nvarchar"
			},
			{
				"name": "oemorganizationtype",
				"type": "nvarchar"
			},
			{
				"name": "OEMManaged",
				"type": "bit"
			},
			{
				"name": "Description",
				"type": "nvarchar"
			},
			{
				"name": "AccountStatus",
				"type": "nvarchar"
			},
			{
				"name": "AccountAddress",
				"type": "nvarchar"
			},
			{
				"name": "GPID",
				"type": "varchar"
			},
			{
				"name": "GPName",
				"type": "nvarchar"
			},
			{
				"name": "PDM",
				"type": "nvarchar"
			},
			{
				"name": "IPDM",
				"type": "nvarchar"
			},
			{
				"name": "PTS",
				"type": "nvarchar"
			},
			{
				"name": "PDMM",
				"type": "nvarchar"
			},
			{
				"name": "PTM",
				"type": "nvarchar"
			},
			{
				"name": "PrimaryRoleType",
				"type": "nvarchar"
			},
			{
				"name": "HQ/DS",
				"type": "nvarchar"
			},
			{
				"name": "Primary",
				"type": "nvarchar"
			},
			{
				"name": "TagName",
				"type": "varchar"
			},
			{
				"name": "ISCALCMastered",
				"type": "bit"
			}
		],
		"typeProperties": {
			"schema": "dbo",
			"table": "TempReport_Scorecard_Detail"
		}
	}
}